MANIFEST.in
setup.cfg
setup.py
versioneer.py
parephase/__init__.py
parephase/_version.py
parephase.egg-info/PKG-INFO
parephase.egg-info/SOURCES.txt
parephase.egg-info/dependency_links.txt
parephase.egg-info/entry_points.txt
parephase.egg-info/requires.txt
parephase.egg-info/top_level.txt