Metadata-Version: 1.0
Name: parephase
Version: 0.1.0
Summary: Detects phasing of 5'PARE data around stop codons
Home-page: https://github.com/kdmurray91/parephase
Author: Kevin D. Murray
Author-email: kdmpapers@gmail.com
License: MPL2
Keywords: bioinformatics PARE RNA
Platform: UNKNOWN
